{
  "type": "frivycat:enraged_nether_wastes",
  "generator": {
    "type": "minecraft:noise",
    "seed": 12389023645,
    "biome_source": {
      "type": "minecraft:fixed",
      "seed": 12389023645,
      "biome": "frivycat:e-nwastes"
    },
    "settings": {
      "name": "minecraft:overworld",
      "bedrock_roof_position": -10,
      "bedrock_floor_position": -64,
      "sea_level": 63,
      "disable_mob_generation": false,
      "noise_caves_enabled": true,
      "aquifers_enabled": false,
      "deepslate_enabled": true,
      "default_block": {
        "Name": "minecraft:netherrack"
      },
      "default_fluid": {
        "Name": "minecraft:lava",
        "Properties": {
          "level": "0"
        }
      },
      "noise": {
        "min_y": -64,
        "height": 512,
        "density_factor": 1,
        "density_offset": -0.46875,
        "size_horizontal": 1,
        "size_vertical": 2,
        "simplex_surface_noise": true,
        "random_density_offset": true,
        "sampling": {
          "xz_scale": 1,
          "y_scale": 1,
          "xz_factor": 80,
          "y_factor": 160
        },
        "bottom_slide": {
          "target": -30,
          "size": 0,
          "offset": 0
        },
        "top_slide": {
          "target": -10,
          "size": 3,
          "offset": 0
        }
      },
      "structures": {
        "structures": {
          "minecraft:bastion_remnant": {
            "spacing": 5,
            "separation": 1,
            "salt": 0
          },
          "minecraft:fortress": {
            "spacing": 5,
            "separation": 1,
            "salt": 0
          }
        }
      }
    }
  }
}